fixpoint_common/__init__.py
fixpoint_common/_storage/__init__.py
fixpoint_common/_storage/definitions.py
fixpoint_common/cache.py
fixpoint_common/callcache/__init__.py
fixpoint_common/callcache/_api_cache.py
fixpoint_common/callcache/_cache_ignored.py
fixpoint_common/callcache/_cache_keyed.py
fixpoint_common/callcache/_converter.py
fixpoint_common/callcache/_decorator.py
fixpoint_common/callcache/_disk.py
fixpoint_common/callcache/_in_mem.py
fixpoint_common/callcache/_shared.py
fixpoint_common/completions/__init__.py
fixpoint_common/completions/chat_completion.py
fixpoint_common/completions/tools.py
fixpoint_common/config.py
fixpoint_common/constants.py
fixpoint_common/errors.py
fixpoint_common/logging.py
fixpoint_common/py.typed
fixpoint_common/sqlite.py
fixpoint_common/types/__init__.py
fixpoint_common/types/_helpers.py
fixpoint_common/types/_shared.py
fixpoint_common/types/basic.py
fixpoint_common/types/callcache.py
fixpoint_common/types/citations.py
fixpoint_common/types/companies.py
fixpoint_common/types/documents.py
fixpoint_common/types/extraction.py
fixpoint_common/types/forms.py
fixpoint_common/types/human.py
fixpoint_common/types/json_extraction.py
fixpoint_common/types/list_api.py
fixpoint_common/types/metadata.py
fixpoint_common/types/parsing.py
fixpoint_common/types/patent_extraction.py
fixpoint_common/types/people.py
fixpoint_common/types/research.py
fixpoint_common/types/sitemap.py
fixpoint_common/types/sources.py
fixpoint_common/types/version.py
fixpoint_common/types/workflow.py
fixpoint_common/utils/__init__.py
fixpoint_common/utils/concurrency.py
fixpoint_common/utils/http.py
fixpoint_common/utils/ids.py
fixpoint_common/utils/retry.py
fixpoint_common/utils/sql.py
fixpoint_common/webresearcher/__init__.py
fixpoint_common/webresearcher/converters.py
fixpoint_common/webresearcher/types.py
fixpoint_common/workflows/__init__.py
fixpoint_common/workflows/_workflow.py
fixpoint_common/workflows/constants.py
fixpoint_common/workflows/human/__init__.py
fixpoint_common-0.28.0.dist-info/LICENSE
fixpoint_common-0.28.0.dist-info/METADATA
fixpoint_common-0.28.0.dist-info/WHEEL
fixpoint_common-0.28.0.dist-info/RECORD
